cloudwatchlogs_logging
