Metadata-Version: 1.1
Name: python-cloudwatchlogs-logging
Version: 0.0.3
Summary: Handler for easy logging to AWS CloudWatchLogs.
Home-page: https://github.com/ImmobilienScout24/python-cloudwatchlogs-logging
Author: Arne Hilmann
Author-email: arne.hilmann@gmail.com
License: Apache License 2.0
Platform: UNKNOWN
Classifier: Development Status :: 2 - Pre-Alpha
Classifier: Environment :: Console
Classifier: Intended Audience :: Developers
Classifier: Intended Audience :: System Administrators
Classifier: Programming Language :: Python
Classifier: Topic :: System :: Networking
Classifier: Topic :: System :: Software Distribution
Classifier: Topic :: System :: Systems Administration
